fetch_use/__init__.py
fetch_use/client.py
fetch_use/py.typed
fetch_use-0.2.0.dist-info/METADATA
fetch_use-0.2.0.dist-info/WHEEL
fetch_use-0.2.0.dist-info/RECORD
