Metadata-Version: 2.4
Name: fetch-use
Version: 0.2.0
Summary: Python client for Browser-Use Fetch HTTP service
Project-URL: Homepage, https://browser-use.com
Project-URL: Documentation, https://docs.browser-use.com
Project-URL: Repository, https://github.com/browser-use/fetch-use
Author-email: Browser-Use <support@browser-use.com>
License: MIT
Keywords: api,fetch,http,proxy,requests
Classifier: Development Status :: 4 - Beta
Classifier: Intended Audience :: Developers
Classifier: License :: OSI Approved :: MIT License
Classifier: Operating System :: OS Independent
Classifier: Programming Language :: Python :: 3
Classifier: Programming Language :: Python :: 3.9
Classifier: Programming Language :: Python :: 3.10
Classifier: Programming Language :: Python :: 3.11
Classifier: Programming Language :: Python :: 3.12
Classifier: Topic :: Internet :: WWW/HTTP
Classifier: Topic :: Software Development :: Libraries :: Python Modules
Requires-Python: >=3.9
Provides-Extra: dev
Requires-Dist: pytest-asyncio>=0.23.0; extra == 'dev'
Requires-Dist: pytest>=8.0.0; extra == 'dev'
Requires-Dist: ruff>=0.4.0; extra == 'dev'
